aioipinfo/__init__.py
aioipinfo/__main__.py
aioipinfo-0.1.1.dist-info/LICENSE
aioipinfo-0.1.1.dist-info/METADATA
aioipinfo-0.1.1.dist-info/WHEEL
aioipinfo-0.1.1.dist-info/top_level.txt
aioipinfo-0.1.1.dist-info/RECORD
