Metadata-Version: 2.1
Name: aioipinfo
Version: 0.1.1
Summary: The aioipinfo Python package
Author: John Gorman
License: MIT License
Project-URL: Homepage, https://github.com/gormaniac/aioipinfo
Project-URL: Documentation, https://gormo.co/aioipinfo/
Requires-Python: >=3.11
License-File: LICENSE
